ahdilaw/__init__.py
ahdilaw/conv2d.py
ahdilaw/special/__init__.py
ahdilaw/special/ctconv2d.py
ahdilaw/special/spconv2d.py
ahdilaw-0.0.1.1.dist-info/METADATA
ahdilaw-0.0.1.1.dist-info/WHEEL
ahdilaw-0.0.1.1.dist-info/top_level.txt
ahdilaw-0.0.1.1.dist-info/RECORD
