Metadata-Version: 2.1
Name: ahdilaw
Version: 0.0.1.1
Summary: Plugin Library for Inertial Filters for Deep Convolutional Networks
Home-page: UNKNOWN
Author: @ahdilaw
License: UNKNOWN
Platform: UNKNOWN
Requires-Python: >=3.7
Requires-Dist: torch
Requires-Dist: pybind11
